CHANGELOG.md
LICENSE
MANIFEST.in
README.md
requirements.txt
setup.py
dag_dq_generator/__init__.py
dag_dq_generator/__version__.py
dag_dq_generator/dag_generator.py
dag_dq_generator.egg-info/PKG-INFO
dag_dq_generator.egg-info/SOURCES.txt
dag_dq_generator.egg-info/dependency_links.txt
dag_dq_generator.egg-info/entry_points.txt
dag_dq_generator.egg-info/not-zip-safe
dag_dq_generator.egg-info/requires.txt
dag_dq_generator.egg-info/top_level.txt
dag_dq_generator/__pycache__/__init__.cpython-38.pyc
dag_dq_generator/__pycache__/__version__.cpython-38.pyc
dag_dq_generator/configs/sample.yml
dag_dq_generator/configs/stage_sample.yml
dag_dq_generator/dags/demo-dev-01.py
dag_dq_generator/dags/stage_test_001.py
dag_dq_generator/templates/_global_macros.py
dag_dq_generator/templates/dag_template.py
dag_dq_generator/templates/dq-anomaly-detector.py
dag_dq_generator/templates/dq_sql_template.sql
dag_dq_generator/tests/__init__.py