Metadata-Version: 1.1
Name: dag-dq-generator
Version: 1.0.5
Summary: DPaaS Airflow DAG (Dynamic Acyclic Graph) and DQ (Data Quality) generator
Home-page: https://git.corp.adobe.com/ccea/dag-dq-generator
Author: CI DMe Data Engineering
Author-email: ccea-data-engineering@adobe.com
License: MIT
Keywords: airflow dag data-quality
Platform: UNKNOWN
Classifier: License :: OSI Approved :: MIT License
Classifier: Programming Language :: Python
Classifier: Programming Language :: Python :: 3
Classifier: Programming Language :: Python :: 3.7
Classifier: Programming Language :: Python :: Implementation :: CPython
Classifier: Programming Language :: Python :: Implementation :: PyPy
